LICENSE
MANIFEST.in
README.md
setup.py
pimanager/VERSION
pimanager/__init__.py
pimanager/admin.py
pimanager/apps.py
pimanager/models.py
pimanager/urls.py
pimanager/views.py
pimanager.egg-info/PKG-INFO
pimanager.egg-info/SOURCES.txt
pimanager.egg-info/dependency_links.txt
pimanager.egg-info/requires.txt
pimanager.egg-info/top_level.txt
pimanager/management/commands/add_action.py
pimanager/management/commands/update_client.py
pimanager/management/commands/update_player.py
pimanager/migrations/0001_initial.py
pimanager/migrations/0002_device_interface.py
pimanager/migrations/0003_device_interface_blank.py
pimanager/migrations/__init__.py
pimanager/static/pimanager/README.md
pimanager/static/pimanager/pimanager.css
pimanager/static/pimanager/client/action.py
pimanager/static/pimanager/client/report_status.py
pimanager/static/pimanager/client_files/pimanager.cron
pimanager/static/pimanager/omxloop/no_media.jpg
pimanager/static/pimanager/omxloop/no_media.png
pimanager/static/pimanager/omxloop/no_media.psd
pimanager/static/pimanager/omxloop/omxloop.py
pimanager/static/pimanager/omxloop/omxloop_init.sh
pimanager/templates/pimanager/actions.html
pimanager/templates/pimanager/base.html
pimanager/templates/pimanager/client_setup.sh
pimanager/templates/pimanager/client_upgrade.sh
pimanager/templates/pimanager/devices.html
pimanager/templates/pimanager/omxloop_setup.sh
pimanager/templates/pimanager/omxloop_upgrade.sh
pimanager/templates/pimanager/power_cycle.html
tests/__init__.py
tests/test_settings.py
tests/tests.py